{
    "data": {
        "itemPage": {
            "itemHeader": {
                "id": "2049128890",
                "name": "Tonkotsu Ramen",
                "imgUrl": "https://img.cdn4dd.com/cdn-cgi/image/fit=contain,width=1200,height=672,format=auto/https://doordash-static.s3.amazonaws.com/media/photos/90785366-46dc-44dd-b02d-1811e63d03ad-retina-large-jpeg",
                "imgUrlList": [
                    {
                        "url": "https://img.cdn4dd.com/u/media/bc3efa46-864a-41fc-9d5d-61e48011369e.jpg",
                        "photoUuid": "bc3efa46-864a-41fc-9d5d-61e48011369e",
                        "__typename": "GenericImage"
                    }
                ],
                "discountPricesList": [],
                "photoCountText": "2 photos",
                "description": "Roasted pork, boiled egg, kikurage mushroom, bamboo shoots, green onion, sprouts, fish cake, roasted seaweed.",
                "displayString": "+$16.49",
                "unitAmount": 1649,
                "currency": "USD",
                "decimalPlaces": 2,
                "specialInstructionsMaxLength": 500,
                "calloutDisplayString": "",
                "minAgeRequirement": 0,
                "foodAlcoholConstraint": "REQUIRES_NONE",
                "dashpassExclusiveItemDisabled": false,
                "isDashpassExclusive": false,
                "shouldDisplayAiDisclaimer": false,
                "quantityLimit": 0,
                "servingSizeDisplayString": null,
                "banners": [],
                "caloricInfoDisplayString": "",
                "dietaryTagsList": [],
                "menuId": "2627785",
                "reviewData": {
                    "ratingDisplayString": "94% (226)",
                    "reviewCount": "4",
                    "itemReviewRankingCount": 0,
                    "consumerItemRating": {
                        "rating": {
                            "ratingType": null,
                            "ratingValue": null,
                            "__typename": "RatingInfo"
                        },
                        "ratingDisplayString": "",
                        "__typename": "ConsumerItemRating"
                    },
                    "__typename": "ReviewData"
                },
                "secondaryDescription": "",
                "terms": null,
                "badges": [],
                "__typename": "ItemHeader"
            },
            "optionLists": [
                {
                    "type": "extra_option",
                    "id": "1373198089",
                    "name": "Spicy Level",
                    "subtitle": "Select 1",
                    "selectionNode": "single_select",
                    "minNumOptions": 1,
                    "maxNumOptions": 1,
                    "minAggregateOptionsQuantity": null,
                    "maxAggregateOptionsQuantity": null,
                    "minOptionChoiceQuantity": null,
                    "maxOptionChoiceQuantity": null,
                    "numFreeOptions": 0,
                    "isOptional": false,
                    "storeId": null,
                    "titleLayout": null,
                    "options": [
                        {
                            "id": "8850925324",
                            "name": "Mild",
                            "unitAmount": 0,
                            "currency": "USD",
                            "displayString": "",
                            "decimalPlaces": 2,
                            "nextCursor": null,
                            "caloricInfoDisplayString": "",
                            "chargeAbove": 0,
                            "chargeAboveDisplayString": "",
                            "defaultQuantity": 0,
                            "dietaryTagsList": [],
                            "optionTagsList": [],
                            "minOptionChoiceQuantity": null,
                            "maxOptionChoiceQuantity": null,
                            "imgUrl": "",
                            "__typename": "FeedOption",
                            "nestedExtrasList": []
                        },
                        {
                            "id": "8850925325",
                            "name": "Non-spicy",
                            "unitAmount": 0,
                            "currency": "USD",
                            "displayString": "",
                            "decimalPlaces": 2,
                            "nextCursor": null,
                            "caloricInfoDisplayString": "",
                            "chargeAbove": 0,
                            "chargeAboveDisplayString": "",
                            "defaultQuantity": 0,
                            "dietaryTagsList": [],
                            "optionTagsList": [],
                            "minOptionChoiceQuantity": null,
                            "maxOptionChoiceQuantity": null,
                            "imgUrl": "",
                            "__typename": "FeedOption",
                            "nestedExtrasList": []
                        },
                        {
                            "id": "8850925323",
                            "name": "Medium",
                            "unitAmount": 0,
                            "currency": "USD",
                            "displayString": "",
                            "decimalPlaces": 2,
                            "nextCursor": null,
                            "caloricInfoDisplayString": "",
                            "chargeAbove": 0,
                            "chargeAboveDisplayString": "",
                            "defaultQuantity": 0,
                            "dietaryTagsList": [],
                            "optionTagsList": [],
                            "minOptionChoiceQuantity": null,
                            "maxOptionChoiceQuantity": null,
                            "imgUrl": "",
                            "__typename": "FeedOption",
                            "nestedExtrasList": []
                        },
                        {
                            "id": "8850925322",
                            "name": "Spicy",
                            "unitAmount": 0,
                            "currency": "USD",
                            "displayString": "",
                            "decimalPlaces": 2,
                            "nextCursor": null,
                            "caloricInfoDisplayString": "",
                            "chargeAbove": 0,
                            "chargeAboveDisplayString": "",
                            "defaultQuantity": 0,
                            "dietaryTagsList": [],
                            "optionTagsList": [],
                            "minOptionChoiceQuantity": null,
                            "maxOptionChoiceQuantity": null,
                            "imgUrl": "",
                            "__typename": "FeedOption",
                            "nestedExtrasList": []
                        },
                        {
                            "id": "8850925321",
                            "name": "Extra Spicy",
                            "unitAmount": 0,
                            "currency": "USD",
                            "displayString": "",
                            "decimalPlaces": 2,
                            "nextCursor": null,
                            "caloricInfoDisplayString": "",
                            "chargeAbove": 0,
                            "chargeAboveDisplayString": "",
                            "defaultQuantity": 0,
                            "dietaryTagsList": [],
                            "optionTagsList": [],
                            "minOptionChoiceQuantity": null,
                            "maxOptionChoiceQuantity": null,
                            "imgUrl": "",
                            "__typename": "FeedOption",
                            "nestedExtrasList": []
                        }
                    ],
                    "validationType": "DEFAULT",
                    "flattenedDefaultNodes": [],
                    "__typename": "OptionList"
                },
                {
                    "type": "extra_option",
                    "id": "1373198088",
                    "name": "Add On Ramen Toppings",
                    "subtitle": "Select up to 18",
                    "selectionNode": "multi_select",
                    "minNumOptions": 0,
                    "maxNumOptions": 18,
                    "minAggregateOptionsQuantity": null,
                    "maxAggregateOptionsQuantity": null,
                    "minOptionChoiceQuantity": null,
                    "maxOptionChoiceQuantity": null,
                    "numFreeOptions": 0,
                    "isOptional": true,
                    "storeId": null,
                    "titleLayout": null,
                    "options": [
                        {
                            "id": "8850925344",
                            "name": "Roasted Pork(2pcs)",
                            "unitAmount": 350,
                            "currency": "USD",
                            "displayString": "+$3.50",
                            "decimalPlaces": 2,
                            "nextCursor": null,
                            "caloricInfoDisplayString": "",
                            "chargeAbove": 0,
                            "chargeAboveDisplayString": "",
                            "defaultQuantity": 0,
                            "dietaryTagsList": [],
                            "optionTagsList": [],
                            "minOptionChoiceQuantity": null,
                            "maxOptionChoiceQuantity": null,
                            "imgUrl": "",
                            "__typename": "FeedOption",
                            "nestedExtrasList": []
                        },
                        {
                            "id": "8850925343",
                            "name": "Shrimps",
                            "unitAmount": 350,
                            "currency": "USD",
                            "displayString": "+$3.50",
                            "decimalPlaces": 2,
                            "nextCursor": null,
                            "caloricInfoDisplayString": "",
                            "chargeAbove": 0,
                            "chargeAboveDisplayString": "",
                            "defaultQuantity": 0,
                            "dietaryTagsList": [],
                            "optionTagsList": [],
                            "minOptionChoiceQuantity": null,
                            "maxOptionChoiceQuantity": null,
                            "imgUrl": "",
                            "__typename": "FeedOption",
                            "nestedExtrasList": []
                        },
                        {
                            "id": "8850925342",
                            "name": "Scallops",
                            "unitAmount": 350,
                            "currency": "USD",
                            "displayString": "+$3.50",
                            "decimalPlaces": 2,
                            "nextCursor": null,
                            "caloricInfoDisplayString": "",
                            "chargeAbove": 0,
                            "chargeAboveDisplayString": "",
                            "defaultQuantity": 0,
                            "dietaryTagsList": [],
                            "optionTagsList": [],
                            "minOptionChoiceQuantity": null,
                            "maxOptionChoiceQuantity": null,
                            "imgUrl": "",
                            "__typename": "FeedOption",
                            "nestedExtrasList": []
                        },
                        {
                            "id": "8850925341",
                            "name": "Chicken",
                            "unitAmount": 350,
                            "currency": "USD",
                            "displayString": "+$3.50",
                            "decimalPlaces": 2,
                            "nextCursor": null,
                            "caloricInfoDisplayString": "",
                            "chargeAbove": 0,
                            "chargeAboveDisplayString": "",
                            "defaultQuantity": 0,
                            "dietaryTagsList": [],
                            "optionTagsList": [],
                            "minOptionChoiceQuantity": null,
                            "maxOptionChoiceQuantity": null,
                            "imgUrl": "",
                            "__typename": "FeedOption",
                            "nestedExtrasList": []
                        },
                        {
                            "id": "8850925340",
                            "name": "Kimichi",
                            "unitAmount": 350,
                            "currency": "USD",
                            "displayString": "+$3.50",
                            "decimalPlaces": 2,
                            "nextCursor": null,
                            "caloricInfoDisplayString": "",
                            "chargeAbove": 0,
                            "chargeAboveDisplayString": "",
                            "defaultQuantity": 0,
                            "dietaryTagsList": [],
                            "optionTagsList": [],
                            "minOptionChoiceQuantity": null,
                            "maxOptionChoiceQuantity": null,
                            "imgUrl": "",
                            "__typename": "FeedOption",
                            "nestedExtrasList": []
                        },
                        {
                            "id": "8850925339",
                            "name": "Extra Noodle",
                            "unitAmount": 350,
                            "currency": "USD",
                            "displayString": "+$3.50",
                            "decimalPlaces": 2,
                            "nextCursor": null,
                            "caloricInfoDisplayString": "",
                            "chargeAbove": 0,
                            "chargeAboveDisplayString": "",
                            "defaultQuantity": 0,
                            "dietaryTagsList": [],
                            "optionTagsList": [],
                            "minOptionChoiceQuantity": null,
                            "maxOptionChoiceQuantity": null,
                            "imgUrl": "",
                            "__typename": "FeedOption",
                            "nestedExtrasList": []
                        },
                        {
                            "id": "8850925338",
                            "name": "Tofu",
                            "unitAmount": 200,
                            "currency": "USD",
                            "displayString": "+$2.00",
                            "decimalPlaces": 2,
                            "nextCursor": null,
                            "caloricInfoDisplayString": "",
                            "chargeAbove": 0,
                            "chargeAboveDisplayString": "",
                            "defaultQuantity": 0,
                            "dietaryTagsList": [],
                            "optionTagsList": [],
                            "minOptionChoiceQuantity": null,
                            "maxOptionChoiceQuantity": null,
                            "imgUrl": "",
                            "__typename": "FeedOption",
                            "nestedExtrasList": []
                        },
                        {
                            "id": "8850925337",
                            "name": "Kikurage Mushroom",
                            "unitAmount": 150,
                            "currency": "USD",
                            "displayString": "+$1.50",
                            "decimalPlaces": 2,
                            "nextCursor": null,
                            "caloricInfoDisplayString": "",
                            "chargeAbove": 0,
                            "chargeAboveDisplayString": "",
                            "defaultQuantity": 0,
                            "dietaryTagsList": [],
                            "optionTagsList": [],
                            "minOptionChoiceQuantity": null,
                            "maxOptionChoiceQuantity": null,
                            "imgUrl": "",
                            "__typename": "FeedOption",
                            "nestedExtrasList": []
                        },
                        {
                            "id": "8850925335",
                            "name": "Fried Garlic",
                            "unitAmount": 150,
                            "currency": "USD",
                            "displayString": "+$1.50",
                            "decimalPlaces": 2,
                            "nextCursor": null,
                            "caloricInfoDisplayString": "",
                            "chargeAbove": 0,
                            "chargeAboveDisplayString": "",
                            "defaultQuantity": 0,
                            "dietaryTagsList": [],
                            "optionTagsList": [],
                            "minOptionChoiceQuantity": null,
                            "maxOptionChoiceQuantity": null,
                            "imgUrl": "",
                            "__typename": "FeedOption",
                            "nestedExtrasList": []
                        },
                        {
                            "id": "8850925334",
                            "name": "Boiled Egg",
                            "unitAmount": 150,
                            "currency": "USD",
                            "displayString": "+$1.50",
                            "decimalPlaces": 2,
                            "nextCursor": null,
                            "caloricInfoDisplayString": "",
                            "chargeAbove": 0,
                            "chargeAboveDisplayString": "",
                            "defaultQuantity": 0,
                            "dietaryTagsList": [],
                            "optionTagsList": [],
                            "minOptionChoiceQuantity": null,
                            "maxOptionChoiceQuantity": null,
                            "imgUrl": "",
                            "__typename": "FeedOption",
                            "nestedExtrasList": []
                        },
                        {
                            "id": "8850925333",
                            "name": "Bamboo Shoots",
                            "unitAmount": 150,
                            "currency": "USD",
                            "displayString": "+$1.50",
                            "decimalPlaces": 2,
                            "nextCursor": null,
                            "caloricInfoDisplayString": "",
                            "chargeAbove": 0,
                            "chargeAboveDisplayString": "",
                            "defaultQuantity": 0,
                            "dietaryTagsList": [],
                            "optionTagsList": [],
                            "minOptionChoiceQuantity": null,
                            "maxOptionChoiceQuantity": null,
                            "imgUrl": "",
                            "__typename": "FeedOption",
                            "nestedExtrasList": []
                        },
                        {
                            "id": "8850925332",
                            "name": "Corn",
                            "unitAmount": 150,
                            "currency": "USD",
                            "displayString": "+$1.50",
                            "decimalPlaces": 2,
                            "nextCursor": null,
                            "caloricInfoDisplayString": "",
                            "chargeAbove": 0,
                            "chargeAboveDisplayString": "",
                            "defaultQuantity": 0,
                            "dietaryTagsList": [],
                            "optionTagsList": [],
                            "minOptionChoiceQuantity": null,
                            "maxOptionChoiceQuantity": null,
                            "imgUrl": "",
                            "__typename": "FeedOption",
                            "nestedExtrasList": []
                        },
                        {
                            "id": "8850925331",
                            "name": "Onion",
                            "unitAmount": 150,
                            "currency": "USD",
                            "displayString": "+$1.50",
                            "decimalPlaces": 2,
                            "nextCursor": null,
                            "caloricInfoDisplayString": "",
                            "chargeAbove": 0,
                            "chargeAboveDisplayString": "",
                            "defaultQuantity": 0,
                            "dietaryTagsList": [],
                            "optionTagsList": [],
                            "minOptionChoiceQuantity": null,
                            "maxOptionChoiceQuantity": null,
                            "imgUrl": "",
                            "__typename": "FeedOption",
                            "nestedExtrasList": []
                        },
                        {
                            "id": "8850925330",
                            "name": "Sprout",
                            "unitAmount": 150,
                            "currency": "USD",
                            "displayString": "+$1.50",
                            "decimalPlaces": 2,
                            "nextCursor": null,
                            "caloricInfoDisplayString": "",
                            "chargeAbove": 0,
                            "chargeAboveDisplayString": "",
                            "defaultQuantity": 0,
                            "dietaryTagsList": [],
                            "optionTagsList": [],
                            "minOptionChoiceQuantity": null,
                            "maxOptionChoiceQuantity": null,
                            "imgUrl": "",
                            "__typename": "FeedOption",
                            "nestedExtrasList": []
                        },
                        {
                            "id": "8850925329",
                            "name": "Roasted Seaweed",
                            "unitAmount": 150,
                            "currency": "USD",
                            "displayString": "+$1.50",
                            "decimalPlaces": 2,
                            "nextCursor": null,
                            "caloricInfoDisplayString": "",
                            "chargeAbove": 0,
                            "chargeAboveDisplayString": "",
                            "defaultQuantity": 0,
                            "dietaryTagsList": [],
                            "optionTagsList": [],
                            "minOptionChoiceQuantity": null,
                            "maxOptionChoiceQuantity": null,
                            "imgUrl": "",
                            "__typename": "FeedOption",
                            "nestedExtrasList": []
                        },
                        {
                            "id": "8850925328",
                            "name": "Fish Cake",
                            "unitAmount": 150,
                            "currency": "USD",
                            "displayString": "+$1.50",
                            "decimalPlaces": 2,
                            "nextCursor": null,
                            "caloricInfoDisplayString": "",
                            "chargeAbove": 0,
                            "chargeAboveDisplayString": "",
                            "defaultQuantity": 0,
                            "dietaryTagsList": [],
                            "optionTagsList": [],
                            "minOptionChoiceQuantity": null,
                            "maxOptionChoiceQuantity": null,
                            "imgUrl": "",
                            "__typename": "FeedOption",
                            "nestedExtrasList": []
                        },
                        {
                            "id": "8850925327",
                            "name": "Extra Soup",
                            "unitAmount": 550,
                            "currency": "USD",
                            "displayString": "+$5.50",
                            "decimalPlaces": 2,
                            "nextCursor": null,
                            "caloricInfoDisplayString": "",
                            "chargeAbove": 0,
                            "chargeAboveDisplayString": "",
                            "defaultQuantity": 0,
                            "dietaryTagsList": [],
                            "optionTagsList": [],
                            "minOptionChoiceQuantity": null,
                            "maxOptionChoiceQuantity": null,
                            "imgUrl": "",
                            "__typename": "FeedOption",
                            "nestedExtrasList": []
                        },
                        {
                            "id": "8850925326",
                            "name": "Beef",
                            "unitAmount": 500,
                            "currency": "USD",
                            "displayString": "+$5.00",
                            "decimalPlaces": 2,
                            "nextCursor": null,
                            "caloricInfoDisplayString": "",
                            "chargeAbove": 0,
                            "chargeAboveDisplayString": "",
                            "defaultQuantity": 0,
                            "dietaryTagsList": [],
                            "optionTagsList": [],
                            "minOptionChoiceQuantity": null,
                            "maxOptionChoiceQuantity": null,
                            "imgUrl": "",
                            "__typename": "FeedOption",
                            "nestedExtrasList": []
                        }
                    ],
                    "validationType": "DEFAULT",
                    "flattenedDefaultNodes": [],
                    "__typename": "OptionList"
                },
                {
                    "type": "item",
                    "id": "recommended_option_2049194130",
                    "name": "Recommended Sides And Apps",
                    "subtitle": "Choose up to 5",
                    "selectionNode": "multi_select",
                    "minNumOptions": 0,
                    "maxNumOptions": 10,
                    "minAggregateOptionsQuantity": null,
                    "maxAggregateOptionsQuantity": null,
                    "minOptionChoiceQuantity": null,
                    "maxOptionChoiceQuantity": null,
                    "numFreeOptions": 0,
                    "isOptional": true,
                    "storeId": null,
                    "titleLayout": null,
                    "options": [
                        {
                            "id": "2049194130",
                            "name": "Spam Musubi",
                            "unitAmount": 599,
                            "currency": "USD",
                            "displayString": "+$5.99",
                            "decimalPlaces": 2,
                            "nextCursor": null,
                            "caloricInfoDisplayString": "",
                            "chargeAbove": 0,
                            "chargeAboveDisplayString": "",
                            "defaultQuantity": 0,
                            "dietaryTagsList": [],
                            "optionTagsList": [],
                            "minOptionChoiceQuantity": null,
                            "maxOptionChoiceQuantity": null,
                            "imgUrl": "",
                            "__typename": "FeedOption",
                            "nestedExtrasList": []
                        },
                        {
                            "id": "2049194141",
                            "name": "Gyoza",
                            "unitAmount": 650,
                            "currency": "USD",
                            "displayString": "+$6.50",
                            "decimalPlaces": 2,
                            "nextCursor": null,
                            "caloricInfoDisplayString": "",
                            "chargeAbove": 0,
                            "chargeAboveDisplayString": "",
                            "defaultQuantity": 0,
                            "dietaryTagsList": [],
                            "optionTagsList": [],
                            "minOptionChoiceQuantity": null,
                            "maxOptionChoiceQuantity": null,
                            "imgUrl": "",
                            "__typename": "FeedOption",
                            "nestedExtrasList": []
                        },
                        {
                            "id": "2048996813",
                            "name": "Macaroni Salad",
                            "unitAmount": 450,
                            "currency": "USD",
                            "displayString": "+$4.50",
                            "decimalPlaces": 2,
                            "nextCursor": null,
                            "caloricInfoDisplayString": "",
                            "chargeAbove": 0,
                            "chargeAboveDisplayString": "",
                            "defaultQuantity": 0,
                            "dietaryTagsList": [],
                            "optionTagsList": [],
                            "minOptionChoiceQuantity": null,
                            "maxOptionChoiceQuantity": null,
                            "imgUrl": "",
                            "__typename": "FeedOption",
                            "nestedExtrasList": []
                        },
                        {
                            "id": "2049194131",
                            "name": "Crab Rangoons",
                            "unitAmount": 699,
                            "currency": "USD",
                            "displayString": "+$6.99",
                            "decimalPlaces": 2,
                            "nextCursor": null,
                            "caloricInfoDisplayString": "",
                            "chargeAbove": 0,
                            "chargeAboveDisplayString": "",
                            "defaultQuantity": 0,
                            "dietaryTagsList": [],
                            "optionTagsList": [],
                            "minOptionChoiceQuantity": null,
                            "maxOptionChoiceQuantity": null,
                            "imgUrl": "",
                            "__typename": "FeedOption",
                            "nestedExtrasList": []
                        },
                        {
                            "id": "2049194140",
                            "name": "Chicken Karage",
                            "unitAmount": 1199,
                            "currency": "USD",
                            "displayString": "+$11.99",
                            "decimalPlaces": 2,
                            "nextCursor": null,
                            "caloricInfoDisplayString": "",
                            "chargeAbove": 0,
                            "chargeAboveDisplayString": "",
                            "defaultQuantity": 0,
                            "dietaryTagsList": [],
                            "optionTagsList": [],
                            "minOptionChoiceQuantity": null,
                            "maxOptionChoiceQuantity": null,
                            "imgUrl": "",
                            "__typename": "FeedOption",
                            "nestedExtrasList": []
                        }
                    ],
                    "validationType": "DEFAULT",
                    "flattenedDefaultNodes": [],
                    "__typename": "OptionList"
                },
                {
                    "type": "item",
                    "id": "recommended_option_2049006784",
                    "name": "Recommended Beverages",
                    "subtitle": "Choose up to 5",
                    "selectionNode": "multi_select",
                    "minNumOptions": 0,
                    "maxNumOptions": 10,
                    "minAggregateOptionsQuantity": null,
                    "maxAggregateOptionsQuantity": null,
                    "minOptionChoiceQuantity": null,
                    "maxOptionChoiceQuantity": null,
                    "numFreeOptions": 0,
                    "isOptional": true,
                    "storeId": null,
                    "titleLayout": null,
                    "options": [
                        {
                            "id": "2049006784",
                            "name": "Can Soda",
                            "unitAmount": 250,
                            "currency": "USD",
                            "displayString": "+$2.50",
                            "decimalPlaces": 2,
                            "nextCursor": null,
                            "caloricInfoDisplayString": "",
                            "chargeAbove": 0,
                            "chargeAboveDisplayString": "",
                            "defaultQuantity": 0,
                            "dietaryTagsList": [],
                            "optionTagsList": [],
                            "minOptionChoiceQuantity": null,
                            "maxOptionChoiceQuantity": null,
                            "imgUrl": "",
                            "__typename": "FeedOption",
                            "nestedExtrasList": []
                        },
                        {
                            "id": "5470085582",
                            "name": "Hawaiian sun",
                            "unitAmount": 225,
                            "currency": "USD",
                            "displayString": "+$2.25",
                            "decimalPlaces": 2,
                            "nextCursor": null,
                            "caloricInfoDisplayString": "",
                            "chargeAbove": 0,
                            "chargeAboveDisplayString": "",
                            "defaultQuantity": 0,
                            "dietaryTagsList": [],
                            "optionTagsList": [],
                            "minOptionChoiceQuantity": null,
                            "maxOptionChoiceQuantity": null,
                            "imgUrl": "",
                            "__typename": "FeedOption",
                            "nestedExtrasList": []
                        },
                        {
                            "id": "4122360644",
                            "name": "Boba Thai Tea",
                            "unitAmount": 559,
                            "currency": "USD",
                            "displayString": "+$5.59",
                            "decimalPlaces": 2,
                            "nextCursor": null,
                            "caloricInfoDisplayString": "",
                            "chargeAbove": 0,
                            "chargeAboveDisplayString": "",
                            "defaultQuantity": 0,
                            "dietaryTagsList": [],
                            "optionTagsList": [],
                            "minOptionChoiceQuantity": null,
                            "maxOptionChoiceQuantity": null,
                            "imgUrl": "",
                            "__typename": "FeedOption",
                            "nestedExtrasList": []
                        },
                        {
                            "id": "4145762881",
                            "name": "Taro Boba Milk Tea",
                            "unitAmount": 559,
                            "currency": "USD",
                            "displayString": "+$5.59",
                            "decimalPlaces": 2,
                            "nextCursor": null,
                            "caloricInfoDisplayString": "",
                            "chargeAbove": 0,
                            "chargeAboveDisplayString": "",
                            "defaultQuantity": 0,
                            "dietaryTagsList": [],
                            "optionTagsList": [],
                            "minOptionChoiceQuantity": null,
                            "maxOptionChoiceQuantity": null,
                            "imgUrl": "",
                            "__typename": "FeedOption",
                            "nestedExtrasList": []
                        },
                        {
                            "id": "4145772863",
                            "name": "Original Boba Milk Tea",
                            "unitAmount": 559,
                            "currency": "USD",
                            "displayString": "+$5.59",
                            "decimalPlaces": 2,
                            "nextCursor": null,
                            "caloricInfoDisplayString": "",
                            "chargeAbove": 0,
                            "chargeAboveDisplayString": "",
                            "defaultQuantity": 0,
                            "dietaryTagsList": [],
                            "optionTagsList": [],
                            "minOptionChoiceQuantity": null,
                            "maxOptionChoiceQuantity": null,
                            "imgUrl": "",
                            "__typename": "FeedOption",
                            "nestedExtrasList": []
                        }
                    ],
                    "validationType": "DEFAULT",
                    "flattenedDefaultNodes": [],
                    "__typename": "OptionList"
                },
                {
                    "type": "item",
                    "id": "drinks_by_doubledash_option_11565606293",
                    "name": "Add Drinks With DoubleDash",
                    "subtitle": "Delivered from Safeway Beer, Wine & Spirits",
                    "selectionNode": "multi_select",
                    "minNumOptions": 0,
                    "maxNumOptions": 10,
                    "minAggregateOptionsQuantity": null,
                    "maxAggregateOptionsQuantity": null,
                    "minOptionChoiceQuantity": null,
                    "maxOptionChoiceQuantity": null,
                    "numFreeOptions": 0,
                    "isOptional": true,
                    "storeId": "2480758",
                    "titleLayout": {
                        "actionUrl": "https://www.doordash.com/drinks_menu_info_modal?O2_store_name=Safeway%20Beer%2C%20Wine%20%26%20Spirits",
                        "__typename": "MessageLayout"
                    },
                    "options": [
                        {
                            "id": "11565606293",
                            "name": "Modelo Especial Mexican Pale Lager Cans (12 fl oz x 18 ct)",
                            "unitAmount": 2874,
                            "currency": "USD",
                            "displayString": "+$28.74",
                            "decimalPlaces": 2,
                            "nextCursor": null,
                            "caloricInfoDisplayString": "",
                            "chargeAbove": 0,
                            "chargeAboveDisplayString": "",
                            "defaultQuantity": 0,
                            "dietaryTagsList": [],
                            "optionTagsList": [],
                            "minOptionChoiceQuantity": null,
                            "maxOptionChoiceQuantity": null,
                            "imgUrl": "",
                            "__typename": "FeedOption",
                            "nestedExtrasList": []
                        },
                        {
                            "id": "9686903317",
                            "name": "Knee Deep Brewing Co. Breaking Bud IPA Cans (16 oz x 4 ct)",
                            "unitAmount": 1724,
                            "currency": "USD",
                            "displayString": "+$17.24",
                            "decimalPlaces": 2,
                            "nextCursor": null,
                            "caloricInfoDisplayString": "",
                            "chargeAbove": 0,
                            "chargeAboveDisplayString": "",
                            "defaultQuantity": 0,
                            "dietaryTagsList": [],
                            "optionTagsList": [],
                            "minOptionChoiceQuantity": null,
                            "maxOptionChoiceQuantity": null,
                            "imgUrl": "",
                            "__typename": "FeedOption",
                            "nestedExtrasList": []
                        },
                        {
                            "id": "7610671644",
                            "name": "Carmenet Vintner's Reserve Chardonnay Bottle (750 ml)",
                            "unitAmount": 919,
                            "currency": "USD",
                            "displayString": "+$9.19",
                            "decimalPlaces": 2,
                            "nextCursor": null,
                            "caloricInfoDisplayString": "",
                            "chargeAbove": 0,
                            "chargeAboveDisplayString": "",
                            "defaultQuantity": 0,
                            "dietaryTagsList": [],
                            "optionTagsList": [],
                            "minOptionChoiceQuantity": null,
                            "maxOptionChoiceQuantity": null,
                            "imgUrl": "",
                            "__typename": "FeedOption",
                            "nestedExtrasList": []
                        }
                    ],
                    "validationType": "DEFAULT",
                    "flattenedDefaultNodes": [],
                    "__typename": "OptionList"
                }
            ],
            "presetCarousels": [],
            "itemType": "HAS_OPTIONS",
            "itemCarousels": [],
            "itemPreferences": {
                "id": "user_preferences_id",
                "title": "User Preferences",
                "specialInstructions": {
                    "title": "Add Special Instructions",
                    "characterMaxLength": 500,
                    "isEnabled": true,
                    "placeholderText": "Add any special requests (e.g., food allergies, extra spicy, etc.) and the store will do its best to accommodate you.",
                    "__typename": "ItemSpecialInstructions"
                },
                "substitutionPreferences": {
                    "title": "If item is unavailable",
                    "substitutionPreferencesList": [
                        {
                            "id": "OPTION_TYPE_SUBSTITUTE",
                            "displayString": "Go with merchant recommendation",
                            "isDefault": true,
                            "value": "substitute",
                            "__typename": "ItemSubstitutionPreference"
                        },
                        {
                            "id": "OPTION_TYPE_REFUND",
                            "displayString": "Refund this item",
                            "isDefault": false,
                            "value": "refund",
                            "__typename": "ItemSubstitutionPreference"
                        },
                        {
                            "id": "OPTION_TYPE_CONTACT",
                            "displayString": "Contact me",
                            "isDefault": false,
                            "value": "contact",
                            "__typename": "ItemSubstitutionPreference"
                        },
                        {
                            "id": "OPTION_TYPE_CANCEL",
                            "displayString": "Cancel the entire order",
                            "isDefault": false,
                            "value": "cancel",
                            "__typename": "ItemSubstitutionPreference"
                        }
                    ],
                    "__typename": "ItemSubstitutionPreferences"
                },
                "__typename": "ItemPreferences"
            },
            "additionalDescriptions": [],
            "__typename": "ItemPage"
        }
    },
    "extensions": {
        "requestInfo": {
            "version": 1,
            "requestId": "a4eb8509-08d1-4129-800f-ed01795fa9d9",
            "correlationId": "a4eb8509-08d1-4129-800f-ed01795fa9d9",
            "ddb": false
        }
    }
}